predictive_punter/__init__.py
predictive_punter/command.py
predictive_punter/date_utils.py
predictive_punter/profiling_utils.py
predictive_punter/provider.py
predictive_punter/race.py
predictive_punter/runner.py
predictive_punter/sample.py
predictive_punter/scrape.py
predictive_punter/seed.py
predictive_punter-1.0.0a4.dist-info/DESCRIPTION.rst
predictive_punter-1.0.0a4.dist-info/METADATA
predictive_punter-1.0.0a4.dist-info/RECORD
predictive_punter-1.0.0a4.dist-info/WHEEL
predictive_punter-1.0.0a4.dist-info/entry_points.txt
predictive_punter-1.0.0a4.dist-info/metadata.json
predictive_punter-1.0.0a4.dist-info/top_level.txt
