Metadata-Version: 2.0
Name: predictive-punter
Version: 1.0.0a4
Summary: Applying predictive analytics to horse racing via Python
Home-page: https://github.com/justjasongreen/predictive_punter
Author: Jason Green
Author-email: justjasongreen@gmail.com
License: MIT
Keywords: predictive analytics horse racing
Platform: UNKNOWN
Classifier: Development Status :: 3 - Alpha
Classifier: Environment :: Console
Classifier: Intended Audience :: Developers
Classifier: Intended Audience :: End Users/Desktop
Classifier: License :: OSI Approved :: MIT License
Classifier: Natural Language :: English
Classifier: Operating System :: OS Independent
Classifier: Programming Language :: Python :: 3.5
Classifier: Topic :: Scientific/Engineering :: Information Analysis
Classifier: Topic :: Software Development :: Libraries :: Python Modules
Requires-Dist: cache-requests
Requires-Dist: lxml
Requires-Dist: numpy
Requires-Dist: punters-client
Requires-Dist: pymongo
Requires-Dist: racing-data
Requires-Dist: redis
Requires-Dist: requests
Requires-Dist: scikit-learn
Requires-Dist: scipy
Provides-Extra: dev
Requires-Dist: bumpversion; extra == 'dev'
Requires-Dist: check-manifest; extra == 'dev'
Provides-Extra: test
Requires-Dist: tox; extra == 'test'
